<?xml version="1.0" encoding="utf-8" ?>
<dwsync>
<file name="red.png" server="C:/xampp/phpMyAdmin/" local="131480520784996975" remote="131480520780000000" Dst="2" />
<file name="mobile.png" server="C:/xampp/phpMyAdmin/" local="131478875499361814" remote="131478875490000000" Dst="2" />
<file name="tablet-ebook-reader.png" server="C:/xampp/phpMyAdmin/" local="131480680244011904" remote="131480680240000000" Dst="2" />
<file name="logo.png" server="C:/xampp/phpMyAdmin/" local="131477884681999373" remote="131477884680000000" Dst="2" />
<file name="Sort_up_font_a11wesome.svg-white.png" server="C:/xampp/phpMyAdmin/" local="131483252618721945" remote="131483252610000000" Dst="2" />
<file name="Mobile-Huawei-P8-Lite-Dual-SIM-16-GBd5a77b.jpg" server="C:/xampp/phpMyAdmin/" local="131481666346770973" remote="131481666340000000" Dst="2" />
<file name="red.png" server="C:/xampp/phpMyAdmin" local="131480520784996975" remote="131480556780000000" Dst="1" />
<file name="mobile.png" server="C:/xampp/phpMyAdmin" local="131478875499361814" remote="131478911490000000" Dst="1" />
<file name="tablet-ebook-reader.png" server="C:/xampp/phpMyAdmin" local="131480680244011904" remote="131480716240000000" Dst="1" />
<file name="1503990105pattern42.png" server="C:/xampp/phpMyAdmin" local="131489319256860370" remote="131489355250000000" Dst="1" />
<file name="logo.png" server="C:/xampp/phpMyAdmin" local="131477884681999373" remote="131477920680000000" Dst="1" />
<file name="Mobile-Huawei-P8-Lite-Dual-SIM-16-GBd5a77b.jpg" server="C:/xampp/phpMyAdmin" local="131481666346770973" remote="131481666340000000" Dst="2" />
<file name="case-logic-vnb-217-backpack-for-17-inch-laptop-8b0abf.jpg" server="C:/xampp/phpMyAdmin" local="131485020159245883" remote="131485020150000000" Dst="2" />
<file name="gameconsole-sony-playstation-4-pro-cuh-2016a-region-2-1-tb.jpg" server="C:/xampp/phpMyAdmin" local="131485020268176926" remote="131485020260000000" Dst="2" />
<file name="jacques-bogart-club-75-eau-de-toilette-for-men-100ml-33dffa.jpg" server="C:/xampp/phpMyAdmin" local="131485020323141776" remote="131485020320000000" Dst="2" />
<file name="samsung-49m6965-curved-smart-led-tv-49-inch-77459c.jpg" server="C:/xampp/phpMyAdmin" local="131485020227844130" remote="131485020220000000" Dst="2" />
<file name="samsung-galaxy-j7-prime-sm-g610fd-dual-sim-mobile-phone-202313.jpg" server="C:/xampp/phpMyAdmin" local="131485020364420118" remote="131485020360000000" Dst="2" />
<file name="techno-te-8100-steam-press-8a6477.jpg" server="C:/xampp/phpMyAdmin" local="131485020632037844" remote="131485020630000000" Dst="2" />
<file name="Finished_Badge.png" server="C:/xampp/phpMyAdmin" local="131485005685510048" remote="131485005680000000" Dst="2" />
<file name="87c954a7.jpg" server="C:/xampp/phpMyAdmin" local="131490857416539357" remote="131490857410000000" Dst="2" />
<file name="ios_app_bg.png" server="C:/xampp/phpMyAdmin" local="131491663611563318" remote="131491699610000000" Dst="1" />
<file name="cafebazaar-digikala.png" server="C:/xampp/phpMyAdmin" local="131491663611523284" remote="131491699610000000" Dst="1" />
<file name="stars.png" server="C:/xampp/phpMyAdmin" local="131502087277366635" remote="131502123270000000" Dst="1" />
<file name="1505548046badge.png" server="C:/xampp/phpMyAdmin" local="131502893098100672" remote="131502929090000000" Dst="1" />
<file name="842064c4-a999-4e56-88b2-0681bba02e24.jpg" server="C:/xampp/phpMyAdmin" local="131506395579333003" remote="131506395570000000" Dst="1" />
<file name="f8459100-98ff-48f3-95e6-7e47af3a3543.jpg" server="C:/xampp/phpMyAdmin" local="131506395579403030" remote="131506395570000000" Dst="1" />
</dwsync>